{"cameraMode":{"drawMode":0,"name":"Shaded","section":"Shading Mode"},"sceneLighting":false,"audioPlay":false,"sceneViewState":{"m_AlwaysRefresh":false,"showFog":true,"showSkybox":false,"showFlares":true,"showImageEffects":true,"showParticleSystems":true,"showVisualEffectGraphs":true,"m_FxEnabled":false},"in2DMode":false,"pivot":{"x":0.399993896484375,"y":0.05999755859375,"z":0.0},"rotation":{"x":0.2645811438560486,"y":0.06069779768586159,"z":-0.01670028455555439,"w":0.9623289108276367},"size":0.5797126293182373,"orthographic":true}